eks_supported_versions/__init__.py
eks_supported_versions/eks_supported_versions.py
eks_supported_versions-0.1.dist-info/LICENSE
eks_supported_versions-0.1.dist-info/METADATA
eks_supported_versions-0.1.dist-info/WHEEL
eks_supported_versions-0.1.dist-info/top_level.txt
eks_supported_versions-0.1.dist-info/RECORD
