Metadata-Version: 2.1
Name: eks-supported-versions
Version: 0.1
Summary: Get the supported eks versions.
Home-page: http://github.com/zawachte/eks_supported_versions
Author: Zachary Wachtel
Author-email: zwachtel11@gmail.com
License: MIT
Platform: UNKNOWN
License-File: LICENSE
